demerge/__init__.py
demerge/py.typed
demerge/data/__init__.py
demerge/data/cdb_20250528.zarr.zip
demerge/data/ddb_20250819.fits.gz
demerge/data/missing.ant
demerge/data/missing.cabin
demerge/data/missing.misti
demerge/data/missing.skychop
demerge/data/missing.wea
demerge/merge/__init__.py
demerge/merge/utils.py
demerge/reduce/__init__.py
demerge/reduce/utils/.git
demerge/reduce/utils/.gitignore
demerge/reduce/utils/README.md
demerge/reduce/utils/poetry.lock
demerge/reduce/utils/pyproject.toml
demerge/reduce/utils/.devcontainer/devcontainer.json
demerge/reduce/utils/.github/workflows/tests.yaml
demerge/reduce/utils/scripts/kid_test.db
demerge/reduce/utils/scripts/aste/.gitkeep
demerge/reduce/utils/scripts/aste/Configure.py
demerge/reduce/utils/scripts/aste/FitSweep.py
demerge/reduce/utils/scripts/aste/SaveFits.py
demerge/reduce/utils/scripts/aste/common.py
demerge/reduce/utils/scripts/aste/current_outdir.conf
demerge/reduce/utils/scripts/aste/flag_KIDs_based_on_FitSweep.py
demerge/reduce/utils/scripts/aste/run_sf.sh
demerge/reduce/utils/scripts/aste/run_sf_2025_for_aste.sh
demerge/reduce/utils/scripts/aste/show_kids_figs.py
demerge/reduce/utils/scripts/aste/util.py
demerge/reduce/utils/scripts/libs/.gitignore
demerge/reduce/utils/scripts/libs/bbsweeplib/NEP.py
demerge/reduce/utils/scripts/libs/bbsweeplib/Prad.py
demerge/reduce/utils/scripts/libs/bbsweeplib/TODcalib.py
demerge/reduce/utils/scripts/libs/bbsweeplib/__init__.py
demerge/reduce/utils/scripts/libs/bbsweeplib/arrays.py
demerge/reduce/utils/scripts/libs/bbsweeplib/cache.py
demerge/reduce/utils/scripts/libs/bbsweeplib/deglitch.py
demerge/reduce/utils/scripts/libs/bbsweeplib/files.py
demerge/reduce/utils/scripts/libs/bbsweeplib/kids.py
demerge/reduce/utils/scripts/libs/bbsweeplib/misc.py
demerge/reduce/utils/scripts/libs/bbsweeplib/power.py
demerge/reduce/utils/scripts/libs/fit/__init__.py
demerge/reduce/utils/scripts/libs/fit/confidence_band.py
demerge/reduce/utils/scripts/libs/fit/expr_with_args.py
demerge-2025.8.4.dist-info/METADATA
demerge-2025.8.4.dist-info/WHEEL
demerge-2025.8.4.dist-info/entry_points.txt
demerge-2025.8.4.dist-info/licenses/LICENSE
demerge-2025.8.4.dist-info/RECORD
