Metadata-Version: 2.4
Name: demerge
Version: 2025.8.4
Summary: DESHIMA merge code for observed datasets
Project-URL: homepage, https://deshima-dev.github.io/demerge
Project-URL: repository, https://github.com/deshima-dev/demerge
Author-email: Akio Taniguchi <taniguchi.akio@gmail.com>, Tatsuya Takekoshi <tatsuya.takekoshi@gmail.com>, Daisuke Naito <naito@naitosystems.com>
License: MIT License
License-File: LICENSE
Keywords: astronomy,data-format,deshima,measurement-set,spectroscopy,submillimeter
Classifier: License :: OSI Approved :: MIT License
Classifier: Programming Language :: Python :: 3
Classifier: Programming Language :: Python :: 3.9
Classifier: Programming Language :: Python :: 3.10
Classifier: Programming Language :: Python :: 3.11
Classifier: Programming Language :: Python :: 3.12
Requires-Python: <3.13,>=3.9
Requires-Dist: astropy<8,>=6
Requires-Dist: dems<2026.0,>=2025.6
Requires-Dist: fire<1.0,>=0.5
Requires-Dist: h5py<4,>=3
Requires-Dist: lmfit<2,>=1
Requires-Dist: matplotlib<4,>=3
Requires-Dist: metpy<2,>=1
Requires-Dist: numpy<3.0,>=1.23
Requires-Dist: pandas-stubs<3,>=2
Requires-Dist: pandas<3,>=2
Requires-Dist: scikit-learn<2,>=1
Requires-Dist: scipy<2,>=1
Requires-Dist: sympy<2,>=1
Requires-Dist: zarr<3,>=2
